TextSpitter/__init__.py
TextSpitter/core.py
TextSpitter/logger.py
TextSpitter/main.py
textspitter-0.4.0.dist-info/licenses/LICENSE
textspitter-0.4.0.dist-info/METADATA
textspitter-0.4.0.dist-info/WHEEL
textspitter-0.4.0.dist-info/top_level.txt
textspitter-0.4.0.dist-info/RECORD
