Metadata-Version: 2.4
Name: textspitter
Version: 0.4.0
Summary: A text-extraction application that facilitates string consumption.
Author-email: Francis Secada <francis.secada@gmail.com>
Project-URL: Homepage, https://github.com/fsecada01/TextSpitter
Project-URL: Issues, https://github.com/fsecada01/TextSpitter/issues
Classifier: Programming Language :: Python :: 3
Classifier: License :: OSI Approved :: MIT License
Classifier: Operating System :: OS Independent
Requires-Python: >=3.9
License-File: LICENSE
Requires-Dist: loguru
Requires-Dist: pymupdf
Requires-Dist: pypdf
Requires-Dist: python-docx
Dynamic: license-file
